huellas/__init__.py
huellas/auxiliar.py
huellas/extract_fp.py
huellas/extraction.py
huellas/gui.py
huellas/gui_processing.py
huellas/regions.py
huellas/segmentation.py
huellas/resources/images/kamlo.png
huellas/resources/images/kamlo_abs.png
huellas/resources/images/mpipimi.png
huellas/resources/images/popuko.png
huellas/resources/images/splash.png
fingerprints_unam_colab-0.22.dist-info/LICENSE
fingerprints_unam_colab-0.22.dist-info/METADATA
fingerprints_unam_colab-0.22.dist-info/WHEEL
fingerprints_unam_colab-0.22.dist-info/entry_points.txt
fingerprints_unam_colab-0.22.dist-info/top_level.txt
fingerprints_unam_colab-0.22.dist-info/RECORD
