Metadata-Version: 2.1
Name: fingerprints-unam-colab
Version: 0.22
Summary: Extraction of fingerprint and palm data from grayscale images.
Home-page: https://github.com/forensics-colab-unam/fingerprints-unam-colab
Author: Arturo Curiel
Author-email: me@arturocuriel.com
License: UNKNOWN
Platform: UNKNOWN
Classifier: Programming Language :: Python :: 3
Classifier: License :: OSI Approved :: MIT License
Classifier: Operating System :: OS Independent
License-File: LICENSE
Requires-Dist: wheel
Requires-Dist: numpy
Requires-Dist: scipy
Requires-Dist: matplotlib
Requires-Dist: opencv-python
Requires-Dist: pandas
Requires-Dist: scikit-image
Requires-Dist: sklearn
Requires-Dist: wxpython
